MANIFEST.in
setup.py
arrayfield_tagsinput/__init__.py
arrayfield_tagsinput/admin.py
arrayfield_tagsinput/exceptions.py
arrayfield_tagsinput/fields.py
arrayfield_tagsinput/metadata.py
arrayfield_tagsinput/tests.py
arrayfield_tagsinput/urls.py
arrayfield_tagsinput/utils.py
arrayfield_tagsinput/views.py
arrayfield_tagsinput/widgets.py
arrayfield_tagsinput.egg-info/PKG-INFO
arrayfield_tagsinput.egg-info/SOURCES.txt
arrayfield_tagsinput.egg-info/dependency_links.txt
arrayfield_tagsinput.egg-info/not-zip-safe
arrayfield_tagsinput.egg-info/requires.txt
arrayfield_tagsinput.egg-info/top_level.txt
arrayfield_tagsinput/static/css/jquery-ui-1.8.18.custom.css
arrayfield_tagsinput/static/css/jquery.tagsinput.css
arrayfield_tagsinput/static/css/base/jquery.ui.accordion.css
arrayfield_tagsinput/static/css/base/jquery.ui.all.css
arrayfield_tagsinput/static/css/base/jquery.ui.autocomplete.css
arrayfield_tagsinput/static/css/base/jquery.ui.base.css
arrayfield_tagsinput/static/css/base/jquery.ui.button.css
arrayfield_tagsinput/static/css/base/jquery.ui.core.css
arrayfield_tagsinput/static/css/base/jquery.ui.datepicker.css
arrayfield_tagsinput/static/css/base/jquery.ui.dialog.css
arrayfield_tagsinput/static/css/base/jquery.ui.menu.css
arrayfield_tagsinput/static/css/base/jquery.ui.progressbar.css
arrayfield_tagsinput/static/css/base/jquery.ui.resizable.css
arrayfield_tagsinput/static/css/base/jquery.ui.selectable.css
arrayfield_tagsinput/static/css/base/jquery.ui.slider.css
arrayfield_tagsinput/static/css/base/jquery.ui.spinner.css
arrayfield_tagsinput/static/css/base/jquery.ui.tabs.css
arrayfield_tagsinput/static/css/base/jquery.ui.theme.css
arrayfield_tagsinput/static/css/base/jquery.ui.tooltip.css
arrayfield_tagsinput/static/css/base/images/ui-bg_flat_0_aaaaaa_40x100.png
arrayfield_tagsinput/static/css/base/images/ui-bg_flat_75_ffffff_40x100.png
arrayfield_tagsinput/static/css/base/images/ui-bg_glass_55_fbf9ee_1x400.png
arrayfield_tagsinput/static/css/base/images/ui-bg_glass_65_ffffff_1x400.png
arrayfield_tagsinput/static/css/base/images/ui-bg_glass_75_dadada_1x400.png
arrayfield_tagsinput/static/css/base/images/ui-bg_glass_75_e6e6e6_1x400.png
arrayfield_tagsinput/static/css/base/images/ui-bg_glass_95_fef1ec_1x400.png
