Metadata-Version: 1.1
Name: arrayfield-tagsinput
Version: 0.0.5
Summary: An app that gives you tag input field for forms
Home-page: http://www.routeatlas.com
Author: Ángel Velásquez, Agustín Cangiani
Author-email: angvp@archlinux.org, cangiani@gmail.com
License: GPL
Platform: UNKNOWN
Classifier: Topic :: Internet :: WWW/HTTP :: Dynamic Content
Classifier: Intended Audience :: Developers
Classifier: Programming Language :: Python
Classifier: Programming Language :: Python :: 2.6
Classifier: Programming Language :: Python :: 2.7
Classifier: Framework :: Django
Classifier: Development Status :: 4 - Beta
Classifier: Operating System :: OS Independent
